pymusly-2.0.0.dist-info/RECORD
pymusly-2.0.0.dist-info/WHEEL
pymusly-2.0.0.dist-info/METADATA
pymusly-2.0.0.dist-info/licenses/LICENSE.musly.txt
pymusly-2.0.0.dist-info/licenses/LICENSE.kissfft.txt
pymusly-2.0.0.dist-info/licenses/LICENSE.resample.txt
pymusly-2.0.0.dist-info/licenses/LICENSE.txt
pymusly/ffmpeg_decode.py
pymusly/__init__.py
pymusly/_pymusly.cpython-311-darwin.so
pymusly/libmusly.dylib
