Metadata-Version: 2.1
Name: pymusly
Version: 2.0.0
Summary: Python bindings to libmusly for performing music similarity computation.
Author-Email: Andreas Bannach <andreas@borntohula.de>
License: MIT License
Classifier: Development Status :: 3 - Alpha
Classifier: License :: OSI Approved :: MIT License
Classifier: Programming Language :: Python :: 3 :: Only
Classifier: Programming Language :: Python :: 3.10
Classifier: Programming Language :: Python :: 3.11
Classifier: Programming Language :: Python :: 3.12
Classifier: Programming Language :: Python :: 3.13
Classifier: Programming Language :: Python :: 3.14
Project-URL: Repository, https://github.com/andban/pymusly.git
Project-URL: Issues, https://github.com/andban/pymusly/issues
Requires-Python: >=3.10
Provides-Extra: doc
Requires-Dist: sphinx<8.2.0,>=7.4.7; extra == "doc"
Provides-Extra: dev
Requires-Dist: cmakelang<0.7.0,>=0.6.13; extra == "dev"
Requires-Dist: gcovr<8.4,>=8.2; extra == "dev"
Requires-Dist: pytest<9.1.0,>=9.0.0; extra == "dev"
Requires-Dist: pytest-cov<7.1,>=7.0; extra == "dev"
Requires-Dist: pytest-mock<3.16.0,>=3.14.0; extra == "dev"
Requires-Dist: PyYAML<6.1.0,>=6.0.2; extra == "dev"
Requires-Dist: ruff<0.10.0,>=0.6.9; extra == "dev"
